{"reason":"benchmark-complete","id":"LEM Fibonacci Prove - rc = 100/fib-ref=2bd8b8c486a95ea4219a2d455f51bdbd644a130d/num-100","report_directory":"/var/tmp/runner/_work/101592e9d6058-23-12-07/lurk-rs/lurk-rs/target/criterion/reports/LEM Fibonacci Prove - rc = 100/fib-ref=2bd8b8c486a95ea4219a2d455f51bdbd644a130d/num-100","iteration_count":[4,4,4,4,4,4,4,4,4,4],"measured_values":[12030608510.0,11983581503.0,12054770606.0,11786424515.0,11987372145.0,12068520447.0,11977267648.0,12097931798.0,11880044167.0,11939462849.0],"unit":"ns","throughput":[{"per_iteration":1700,"unit":"elements"}],"typical":{"estimate":2995149604.7,"lower_bound":2980521679.025,"upper_bound":3008020508.8,"unit":"ns"},"mean":{"estimate":2995149604.7,"lower_bound":2980521679.025,"upper_bound":3008020508.8,"unit":"ns"},"median":{"estimate":2996369206.0,"lower_bound":2982163976.875,"upper_bound":3013692651.5,"unit":"ns"},"median_abs_dev":{"estimate":21369409.68664214,"lower_bound":2340230.3142026067,"upper_bound":37788731.44574091,"unit":"ns"},"slope":null,"change":null}
{"reason":"benchmark-complete","id":"LEM Fibonacci Prove - rc = 100/fib-ref=2bd8b8c486a95ea4219a2d455f51bdbd644a130d/num-200","report_directory":"/var/tmp/runner/_work/101592e9d6058-23-12-07/lurk-rs/lurk-rs/target/criterion/reports/LEM Fibonacci Prove - rc = 100/fib-ref=2bd8b8c486a95ea4219a2d455f51bdbd644a130d/num-200","iteration_count":[2,2,2,2,2,2,2,2,2,2],"measured_values":[12165516864.0,12307525500.0,12221098403.0,12238164198.0,12121233429.0,12201069118.0,12179612120.0,11999249976.0,12282268938.0,12256630904.0],"unit":"ns","throughput":[{"per_iteration":3300,"unit":"elements"}],"typical":{"estimate":6098618472.5,"lower_bound":6070455981.585,"upper_bound":6122628868.1,"unit":"ns"},"mean":{"estimate":6098618472.5,"lower_bound":6070455981.585,"upper_bound":6122628868.1,"unit":"ns"},"median":{"estimate":6105541880.25,"lower_bound":6075211387.25,"upper_bound":6130108284.0,"unit":"ns"},"median_abs_dev":{"estimate":33771418.32643747,"lower_bound":13170121.261833608,"upper_bound":68005069.07056868,"unit":"ns"},"slope":null,"change":null}
{"reason":"group-complete","group_name":"LEM Fibonacci Prove - rc = 100","benchmarks":["LEM Fibonacci Prove - rc = 100/fib-ref=2bd8b8c486a95ea4219a2d455f51bdbd644a130d/num-100","LEM Fibonacci Prove - rc = 100/fib-ref=2bd8b8c486a95ea4219a2d455f51bdbd644a130d/num-200"],"report_directory":"/var/tmp/runner/_work/101592e9d6058-23-12-07/lurk-rs/lurk-rs/target/criterion/reports/LEM Fibonacci Prove - rc = 100"}
{"reason":"benchmark-complete","id":"LEM Fibonacci Prove - rc = 600/fib-ref=2bd8b8c486a95ea4219a2d455f51bdbd644a130d/num-100","report_directory":"/var/tmp/runner/_work/101592e9d6058-23-12-07/lurk-rs/lurk-rs/target/criterion/reports/LEM Fibonacci Prove - rc = 600/fib-ref=2bd8b8c486a95ea4219a2d455f51bdbd644a130d/num-100","iteration_count":[5,5,5,5,5,5,5,5,5,5],"measured_values":[13348747349.0,13299245417.0,13285203188.0,13346600356.0,13372906399.0,13353779758.0,13370692101.0,13380873652.0,13270731757.0,13273430320.0],"unit":"ns","throughput":[{"per_iteration":1800,"unit":"elements"}],"typical":{"estimate":2666044205.94,"lower_bound":2660879841.0600004,"upper_bound":2670950597.8,"unit":"ns"},"mean":{"estimate":2666044205.94,"lower_bound":2660879841.0600004,"upper_bound":2670950597.8,"unit":"ns"},"median":{"estimate":2669534770.5,"lower_bound":2657040637.6,"upper_bound":2674138420.2,"unit":"ns"},"median_abs_dev":{"estimate":8663179.464158032,"lower_bound":1064418.1216228716,"upper_bound":14420031.395053126,"unit":"ns"},"slope":null,"change":null}
{"reason":"benchmark-complete","id":"LEM Fibonacci Prove - rc = 600/fib-ref=2bd8b8c486a95ea4219a2d455f51bdbd644a130d/num-200","report_directory":"/var/tmp/runner/_work/101592e9d6058-23-12-07/lurk-rs/lurk-rs/target/criterion/reports/LEM Fibonacci Prove - rc = 600/fib-ref=2bd8b8c486a95ea4219a2d455f51bdbd644a130d/num-200","iteration_count":[3,3,3,3,3,3,3,3,3,3],"measured_values":[17155835965.0,17222296787.0,17218760789.0,17417063415.0,17221103837.0,17455230598.0,17516059054.0,17474265471.0,17231501388.0,17269800046.0],"unit":"ns","throughput":[{"per_iteration":3600,"unit":"elements"}],"typical":{"estimate":5772730578.333334,"lower_bound":5747866738.321668,"upper_bound":5799241256.666666,"unit":"ns"},"mean":{"estimate":5772730578.333334,"lower_bound":5747866738.321668,"upper_bound":5799241256.666666,"unit":"ns"},"median":{"estimate":5750216905.666666,"lower_bound":5740176262.666667,"upper_bound":5818410199.333333,"unit":"ns"},"median_abs_dev":{"estimate":31308725.87215806,"lower_bound":1168523.0300545692,"upper_bound":64714597.56138576,"unit":"ns"},"slope":null,"change":null}
{"reason":"group-complete","group_name":"LEM Fibonacci Prove - rc = 600","benchmarks":["LEM Fibonacci Prove - rc = 600/fib-ref=2bd8b8c486a95ea4219a2d455f51bdbd644a130d/num-100","LEM Fibonacci Prove - rc = 600/fib-ref=2bd8b8c486a95ea4219a2d455f51bdbd644a130d/num-200"],"report_directory":"/var/tmp/runner/_work/101592e9d6058-23-12-07/lurk-rs/lurk-rs/target/criterion/reports/LEM Fibonacci Prove - rc = 600"}
