{"reason":"benchmark-complete","id":"LEM Fibonacci Prove - rc = 100/fib-ref=993e958a6a9c0a03ba84914fae7701c873f7bbc0/num-100","report_directory":"/var/tmp/runner/_work/82bb97d75b7a0-24-01-04/lurk-rs/lurk-rs/target/criterion/reports/LEM Fibonacci Prove - rc = 100/fib-ref=993e958a6a9c0a03ba84914fae7701c873f7bbc0/num-100","iteration_count":[5,5,5,5,5,5,5,5,5,5],"measured_values":[11804470004.0,11844187195.0,11854672819.0,11846531154.0,11813537065.0,11804253919.0,11814048293.0,11827515175.0,11828599406.0,11824354529.0],"unit":"ns","throughput":[{"per_iteration":1100,"unit":"elements"}],"typical":{"estimate":2365243391.1800003,"lower_bound":2363184853.48,"upper_bound":2367372564.4104996,"unit":"ns"},"mean":{"estimate":2365243391.1800003,"lower_bound":2363184853.48,"upper_bound":2367372564.4104996,"unit":"ns"},"median":{"estimate":2365186970.4,"lower_bound":2361851829.7,"upper_bound":2368837439.0,"unit":"ns"},"median_abs_dev":{"estimate":4544188.193124533,"lower_bound":629345.452846602,"upper_bound":5996396.053422973,"unit":"ns"},"slope":null,"change":null}
{"reason":"benchmark-complete","id":"LEM Fibonacci Prove - rc = 100/fib-ref=993e958a6a9c0a03ba84914fae7701c873f7bbc0/num-200","report_directory":"/var/tmp/runner/_work/82bb97d75b7a0-24-01-04/lurk-rs/lurk-rs/target/criterion/reports/LEM Fibonacci Prove - rc = 100/fib-ref=993e958a6a9c0a03ba84914fae7701c873f7bbc0/num-200","iteration_count":[3,3,3,3,3,3,3,3,3,3],"measured_values":[13937694309.0,13883096169.0,13895339267.0,13899364925.0,13878387855.0,13879447720.0,13922477038.0,13882471356.0,13885700654.0,13896645149.0],"unit":"ns","throughput":[{"per_iteration":2100,"unit":"elements"}],"typical":{"estimate":4632020814.733333,"lower_bound":4628589083.378333,"upper_bound":4636269046.8324995,"unit":"ns"},"mean":{"estimate":4632020814.733333,"lower_bound":4628589083.378333,"upper_bound":4636269046.8324995,"unit":"ns"},"median":{"estimate":4630173320.166667,"lower_bound":4627090648.166666,"upper_bound":4636520364.5,"unit":"ns"},"median_abs_dev":{"estimate":4174400.8257898064,"lower_bound":747140.4423365482,"upper_bound":9694811.172283167,"unit":"ns"},"slope":null,"change":null}
{"reason":"group-complete","group_name":"LEM Fibonacci Prove - rc = 100","benchmarks":["LEM Fibonacci Prove - rc = 100/fib-ref=993e958a6a9c0a03ba84914fae7701c873f7bbc0/num-100","LEM Fibonacci Prove - rc = 100/fib-ref=993e958a6a9c0a03ba84914fae7701c873f7bbc0/num-200"],"report_directory":"/var/tmp/runner/_work/82bb97d75b7a0-24-01-04/lurk-rs/lurk-rs/target/criterion/reports/LEM Fibonacci Prove - rc = 100"}
{"reason":"benchmark-complete","id":"LEM Fibonacci Prove - rc = 600/fib-ref=993e958a6a9c0a03ba84914fae7701c873f7bbc0/num-100","report_directory":"/var/tmp/runner/_work/82bb97d75b7a0-24-01-04/lurk-rs/lurk-rs/target/criterion/reports/LEM Fibonacci Prove - rc = 600/fib-ref=993e958a6a9c0a03ba84914fae7701c873f7bbc0/num-100","iteration_count":[6,6,6,6,6,6,6,6,6,6],"measured_values":[11926413155.0,11961787397.0,11919319905.0,11886821578.0,11876235418.0,11867155817.0,11872981887.0,11901904312.0,11910813070.0,11913851341.0],"unit":"ns","throughput":[{"per_iteration":1200,"unit":"elements"}],"typical":{"estimate":1983954731.3333335,"lower_bound":1981211765.7741666,"upper_bound":1986890044.9437504,"unit":"ns"},"mean":{"estimate":1983954731.3333335,"lower_bound":1981211765.7741666,"upper_bound":1986890044.9437504,"unit":"ns"},"median":{"estimate":1984393115.1666667,"lower_bound":1979372569.6666667,"upper_bound":1986688708.0,"unit":"ns"},"median_abs_dev":{"estimate":4891539.2515077,"lower_bound":1051019.445590616,"upper_bound":9064589.18162155,"unit":"ns"},"slope":null,"change":null}
{"reason":"benchmark-complete","id":"LEM Fibonacci Prove - rc = 600/fib-ref=993e958a6a9c0a03ba84914fae7701c873f7bbc0/num-200","report_directory":"/var/tmp/runner/_work/82bb97d75b7a0-24-01-04/lurk-rs/lurk-rs/target/criterion/reports/LEM Fibonacci Prove - rc = 600/fib-ref=993e958a6a9c0a03ba84914fae7701c873f7bbc0/num-200","iteration_count":[3,3,3,3,3,3,3,3,3,3],"measured_values":[13474086208.0,13465980763.0,13470086423.0,13470930310.0,13466987053.0,13458283682.0,13467612144.0,13482414418.0,13477014855.0,13476051178.0],"unit":"ns","throughput":[{"per_iteration":2400,"unit":"elements"}],"typical":{"estimate":4490314901.133333,"lower_bound":4488965931.433333,"upper_bound":4491627997.966667,"unit":"ns"},"mean":{"estimate":4490314901.133333,"lower_bound":4488965931.433333,"upper_bound":4491627997.966667,"unit":"ns"},"median":{"estimate":4490169455.5,"lower_bound":4488932151.166666,"upper_bound":4492017059.333333,"unit":"ns"},"median_abs_dev":{"estimate":2002855.4239422083,"lower_bound":417048.9479949585,"upper_bound":3981360.8730171863,"unit":"ns"},"slope":null,"change":null}
{"reason":"group-complete","group_name":"LEM Fibonacci Prove - rc = 600","benchmarks":["LEM Fibonacci Prove - rc = 600/fib-ref=993e958a6a9c0a03ba84914fae7701c873f7bbc0/num-100","LEM Fibonacci Prove - rc = 600/fib-ref=993e958a6a9c0a03ba84914fae7701c873f7bbc0/num-200"],"report_directory":"/var/tmp/runner/_work/82bb97d75b7a0-24-01-04/lurk-rs/lurk-rs/target/criterion/reports/LEM Fibonacci Prove - rc = 600"}
