{"reason":"benchmark-complete","id":"LEM Fibonacci Prove - rc = 100/ref=1df2666f6be3bc5809727d776afad4fdf00c56b3/num-100","report_directory":"/var/tmp/runner/_work/47bd20f05dd83-24-02-22/lurk-rs/lurk-rs/target/criterion/reports/LEM Fibonacci Prove - rc = 100/ref=1df2666f6be3bc5809727d776afad4fdf00c56b3/num-100","iteration_count":[1,1,1,1,1,1,1,1,1,1],"measured_values":[1466789683.0,1447676209.0,1449127556.0,1444692769.0,1456530909.0,1445830146.0,1460393229.0,1441705362.0,1458321359.0,1446936503.0],"unit":"ns","throughput":[{"per_iteration":800,"unit":"elements"}],"typical":{"estimate":1451800372.5,"lower_bound":1447223759.3,"upper_bound":1456786605.8,"unit":"ns"},"mean":{"estimate":1451800372.5,"lower_bound":1447223759.3,"upper_bound":1456786605.8,"unit":"ns"},"median":{"estimate":1448401882.5,"lower_bound":1445814636.0,"upper_bound":1458321359.0,"unit":"ns"},"median_abs_dev":{"estimate":7713696.347254515,"lower_bound":1368486.4776045084,"upper_bound":13853315.561154485,"unit":"ns"},"slope":null,"change":null}
{"reason":"benchmark-complete","id":"LEM Fibonacci Prove - rc = 100/ref=1df2666f6be3bc5809727d776afad4fdf00c56b3/num-200","report_directory":"/var/tmp/runner/_work/47bd20f05dd83-24-02-22/lurk-rs/lurk-rs/target/criterion/reports/LEM Fibonacci Prove - rc = 100/ref=1df2666f6be3bc5809727d776afad4fdf00c56b3/num-200","iteration_count":[1,1,1,1,1,1,1,1,1,1],"measured_values":[2783027399.0,2784954156.0,2769159559.0,2772829575.0,2783841455.0,2778175512.0,2790191795.0,2778859986.0,2757657567.0,2772760754.0],"unit":"ns","throughput":[{"per_iteration":1500,"unit":"elements"}],"typical":{"estimate":2777145775.8,"lower_bound":2771391803.9449997,"upper_bound":2782284129.5,"unit":"ns"},"mean":{"estimate":2777145775.8,"lower_bound":2771391803.9449997,"upper_bound":2782284129.5,"unit":"ns"},"median":{"estimate":2778517749.0,"lower_bound":2770994567.0,"upper_bound":2783990777.5,"unit":"ns"},"median_abs_dev":{"estimate":8484303.6290735,"lower_bound":1428304.9387425184,"upper_bound":15717352.925661206,"unit":"ns"},"slope":null,"change":null}
{"reason":"group-complete","group_name":"LEM Fibonacci Prove - rc = 100","benchmarks":["LEM Fibonacci Prove - rc = 100/ref=1df2666f6be3bc5809727d776afad4fdf00c56b3/num-100","LEM Fibonacci Prove - rc = 100/ref=1df2666f6be3bc5809727d776afad4fdf00c56b3/num-200"],"report_directory":"/var/tmp/runner/_work/47bd20f05dd83-24-02-22/lurk-rs/lurk-rs/target/criterion/reports/LEM Fibonacci Prove - rc = 100"}
{"reason":"benchmark-complete","id":"LEM Fibonacci Prove - rc = 600/ref=1df2666f6be3bc5809727d776afad4fdf00c56b3/num-100","report_directory":"/var/tmp/runner/_work/47bd20f05dd83-24-02-22/lurk-rs/lurk-rs/target/criterion/reports/LEM Fibonacci Prove - rc = 600/ref=1df2666f6be3bc5809727d776afad4fdf00c56b3/num-100","iteration_count":[1,1,1,1,1,1,1,1,1,1],"measured_values":[1867524696.0,1829329054.0,1819777290.0,1814750984.0,1823278147.0,1820565596.0,1829831358.0,1818866818.0,1817980439.0,1819016681.0],"unit":"ns","throughput":[{"per_iteration":1200,"unit":"elements"}],"typical":{"estimate":1826092106.3,"lower_bound":1819306697.7,"upper_bound":1836247455.7,"unit":"ns"},"mean":{"estimate":1826092106.3,"lower_bound":1819306697.7,"upper_bound":1836247455.7,"unit":"ns"},"median":{"estimate":1820171443.0,"lower_bound":1818498560.0,"upper_bound":1829329054.0,"unit":"ns"},"median_abs_dev":{"estimate":3927190.870678425,"lower_bound":674932.8816175461,"upper_bound":12502457.197237015,"unit":"ns"},"slope":null,"change":null}
{"reason":"benchmark-complete","id":"LEM Fibonacci Prove - rc = 600/ref=1df2666f6be3bc5809727d776afad4fdf00c56b3/num-200","report_directory":"/var/tmp/runner/_work/47bd20f05dd83-24-02-22/lurk-rs/lurk-rs/target/criterion/reports/LEM Fibonacci Prove - rc = 600/ref=1df2666f6be3bc5809727d776afad4fdf00c56b3/num-200","iteration_count":[1,1,1,1,1,1,1,1,1,1],"measured_values":[3022982978.0,3023125623.0,3022237440.0,3015989637.0,3037059150.0,3014883053.0,3053958264.0,3019522392.0,3058527632.0,3012980027.0],"unit":"ns","throughput":[{"per_iteration":1800,"unit":"elements"}],"typical":{"estimate":3028126619.6,"lower_bound":3019329793.6,"upper_bound":3038405290.425,"unit":"ns"},"mean":{"estimate":3028126619.6,"lower_bound":3019329793.6,"upper_bound":3038405290.425,"unit":"ns"},"median":{"estimate":3022610209.0,"lower_bound":3015989637.0,"upper_bound":3038541943.5,"unit":"ns"},"median_abs_dev":{"estimate":10635970.577573776,"lower_bound":764152.7828335762,"upper_bound":25054625.971591473,"unit":"ns"},"slope":null,"change":null}
{"reason":"group-complete","group_name":"LEM Fibonacci Prove - rc = 600","benchmarks":["LEM Fibonacci Prove - rc = 600/ref=1df2666f6be3bc5809727d776afad4fdf00c56b3/num-100","LEM Fibonacci Prove - rc = 600/ref=1df2666f6be3bc5809727d776afad4fdf00c56b3/num-200"],"report_directory":"/var/tmp/runner/_work/47bd20f05dd83-24-02-22/lurk-rs/lurk-rs/target/criterion/reports/LEM Fibonacci Prove - rc = 600"}
