{"reason":"benchmark-complete","id":"LEM Fibonacci Prove - rc = 100/ref=51903719a1c5e54692a63f70c65a31c6b9922286/num-100","report_directory":"/var/tmp/runner/_work/4bb46c5359b88-24-02-15/lurk-rs/lurk-rs/target/criterion/reports/LEM Fibonacci Prove - rc = 100/ref=51903719a1c5e54692a63f70c65a31c6b9922286/num-100","iteration_count":[1,1,1,1,1,1,1,1,1,1],"measured_values":[1463879618.0,1487292690.0,1467770213.0,1474169580.0,1463575711.0,1466169691.0,1464517797.0,1476757744.0,1461769034.0,1452511785.0],"unit":"ns","throughput":[{"per_iteration":800,"unit":"elements"}],"typical":{"estimate":1467841386.3,"lower_bound":1462378765.6,"upper_bound":1473613026.0,"unit":"ns"},"mean":{"estimate":1467841386.3,"lower_bound":1462378765.6,"upper_bound":1473613026.0,"unit":"ns"},"median":{"estimate":1465343744.0,"lower_bound":1462824326.0,"upper_bound":1474169580.0,"unit":"ns"},"median_abs_dev":{"estimate":4448673.91372025,"lower_bound":923654.594501853,"upper_bound":16403376.396381855,"unit":"ns"},"slope":null,"change":null}
{"reason":"benchmark-complete","id":"LEM Fibonacci Prove - rc = 100/ref=51903719a1c5e54692a63f70c65a31c6b9922286/num-200","report_directory":"/var/tmp/runner/_work/4bb46c5359b88-24-02-15/lurk-rs/lurk-rs/target/criterion/reports/LEM Fibonacci Prove - rc = 100/ref=51903719a1c5e54692a63f70c65a31c6b9922286/num-200","iteration_count":[1,1,1,1,1,1,1,1,1,1],"measured_values":[2803322048.0,2808777690.0,2794180473.0,2784879864.0,2800068637.0,2792044798.0,2765919122.0,2789420509.0,2816221608.0,2780745978.0],"unit":"ns","throughput":[{"per_iteration":1500,"unit":"elements"}],"typical":{"estimate":2793558072.7,"lower_bound":2784727382.4,"upper_bound":2801982767.6,"unit":"ns"},"mean":{"estimate":2793558072.7,"lower_bound":2784727382.4,"upper_bound":2801982767.6,"unit":"ns"},"median":{"estimate":2793112635.5,"lower_bound":2784879864.0,"upper_bound":2804423163.5,"unit":"ns"},"median_abs_dev":{"estimate":13671190.756487846,"lower_bound":3528561.2505555153,"upper_bound":25315035.020068288,"unit":"ns"},"slope":null,"change":null}
{"reason":"group-complete","group_name":"LEM Fibonacci Prove - rc = 100","benchmarks":["LEM Fibonacci Prove - rc = 100/ref=51903719a1c5e54692a63f70c65a31c6b9922286/num-100","LEM Fibonacci Prove - rc = 100/ref=51903719a1c5e54692a63f70c65a31c6b9922286/num-200"],"report_directory":"/var/tmp/runner/_work/4bb46c5359b88-24-02-15/lurk-rs/lurk-rs/target/criterion/reports/LEM Fibonacci Prove - rc = 100"}
{"reason":"benchmark-complete","id":"LEM Fibonacci Prove - rc = 600/ref=51903719a1c5e54692a63f70c65a31c6b9922286/num-100","report_directory":"/var/tmp/runner/_work/4bb46c5359b88-24-02-15/lurk-rs/lurk-rs/target/criterion/reports/LEM Fibonacci Prove - rc = 600/ref=51903719a1c5e54692a63f70c65a31c6b9922286/num-100","iteration_count":[1,1,1,1,1,1,1,1,1,1],"measured_values":[1859656268.0,1845391697.0,1848825069.0,1852480245.0,1855770090.0,1889127149.0,1860310529.0,1858188729.0,1852875016.0,1859422851.0],"unit":"ns","throughput":[{"per_iteration":1200,"unit":"elements"}],"typical":{"estimate":1858204764.3,"lower_bound":1852386979.4,"upper_bound":1866330131.2,"unit":"ns"},"mean":{"estimate":1858204764.3,"lower_bound":1852386979.4,"upper_bound":1866330131.2,"unit":"ns"},"median":{"estimate":1856979409.5,"lower_bound":1850850042.5,"upper_bound":1859866690.0,"unit":"ns"},"median_abs_dev":{"estimate":5511945.689043403,"lower_bound":831067.7087455988,"upper_bound":12948243.133422732,"unit":"ns"},"slope":null,"change":null}
{"reason":"benchmark-complete","id":"LEM Fibonacci Prove - rc = 600/ref=51903719a1c5e54692a63f70c65a31c6b9922286/num-200","report_directory":"/var/tmp/runner/_work/4bb46c5359b88-24-02-15/lurk-rs/lurk-rs/target/criterion/reports/LEM Fibonacci Prove - rc = 600/ref=51903719a1c5e54692a63f70c65a31c6b9922286/num-200","iteration_count":[1,1,1,1,1,1,1,1,1,1],"measured_values":[3064522802.0,3062904996.0,3069549739.0,3085666495.0,3122319140.0,3117638384.0,3082394485.0,3072918933.0,3065845384.0,3059387309.0],"unit":"ns","throughput":[{"per_iteration":1800,"unit":"elements"}],"typical":{"estimate":3080314766.7,"lower_bound":3068423127.0,"upper_bound":3094682046.4,"unit":"ns"},"mean":{"estimate":3080314766.7,"lower_bound":3068423127.0,"upper_bound":3094682046.4,"unit":"ns"},"median":{"estimate":3071234336.0,"lower_bound":3064522802.0,"upper_bound":3100016434.5,"unit":"ns"},"median_abs_dev":{"estimate":14447557.939204574,"lower_bound":2425540.96993804,"upper_bound":33065990.58726132,"unit":"ns"},"slope":null,"change":null}
{"reason":"group-complete","group_name":"LEM Fibonacci Prove - rc = 600","benchmarks":["LEM Fibonacci Prove - rc = 600/ref=51903719a1c5e54692a63f70c65a31c6b9922286/num-100","LEM Fibonacci Prove - rc = 600/ref=51903719a1c5e54692a63f70c65a31c6b9922286/num-200"],"report_directory":"/var/tmp/runner/_work/4bb46c5359b88-24-02-15/lurk-rs/lurk-rs/target/criterion/reports/LEM Fibonacci Prove - rc = 600"}
