{"reason":"benchmark-complete","id":"LEM Fibonacci Prove - rc = 100/ref=359e6a17ae371af4585cceba7dfaca98f4415667/num-100","report_directory":"/var/tmp/runner/_work/5584f24c54eff-24-02-21/lurk-rs/lurk-rs/target/criterion/reports/LEM Fibonacci Prove - rc = 100/ref=359e6a17ae371af4585cceba7dfaca98f4415667/num-100","iteration_count":[1,1,1,1,1,1,1,1,1,1],"measured_values":[1450027145.0,1452948080.0,1452748869.0,1449129398.0,1449862414.0,1456891349.0,1460123973.0,1465532760.0,1470810306.0,1469901506.0],"unit":"ns","throughput":[{"per_iteration":800,"unit":"elements"}],"typical":{"estimate":1457797580.0,"lower_bound":1453235735.9,"upper_bound":1462884740.8,"unit":"ns"},"mean":{"estimate":1457797580.0,"lower_bound":1453235735.9,"upper_bound":1462884740.8,"unit":"ns"},"median":{"estimate":1454919714.5,"lower_bound":1450027145.0,"upper_bound":1465532760.0,"unit":"ns"},"median_abs_dev":{"estimate":7606893.551650643,"lower_bound":787614.9274170399,"upper_bound":13659601.2724936,"unit":"ns"},"slope":null,"change":null}
{"reason":"benchmark-complete","id":"LEM Fibonacci Prove - rc = 100/ref=359e6a17ae371af4585cceba7dfaca98f4415667/num-200","report_directory":"/var/tmp/runner/_work/5584f24c54eff-24-02-21/lurk-rs/lurk-rs/target/criterion/reports/LEM Fibonacci Prove - rc = 100/ref=359e6a17ae371af4585cceba7dfaca98f4415667/num-200","iteration_count":[1,1,1,1,1,1,1,1,1,1],"measured_values":[2746758777.0,2777108507.0,2795478464.0,2796911653.0,2759591535.0,2769440799.0,2784274908.0,2782487089.0,2778778446.0,2787666781.0],"unit":"ns","throughput":[{"per_iteration":1500,"unit":"elements"}],"typical":{"estimate":2777849695.9,"lower_bound":2768142074.8,"upper_bound":2786458981.9674997,"unit":"ns"},"mean":{"estimate":2777849695.9,"lower_bound":2768142074.8,"upper_bound":2786458981.9674997,"unit":"ns"},"median":{"estimate":2780632767.5,"lower_bound":2768350021.0,"upper_bound":2789876686.0,"unit":"ns"},"median_abs_dev":{"estimate":13510920.216733217,"lower_bound":3839705.6114315987,"upper_bound":26602979.995402694,"unit":"ns"},"slope":null,"change":null}
{"reason":"group-complete","group_name":"LEM Fibonacci Prove - rc = 100","benchmarks":["LEM Fibonacci Prove - rc = 100/ref=359e6a17ae371af4585cceba7dfaca98f4415667/num-100","LEM Fibonacci Prove - rc = 100/ref=359e6a17ae371af4585cceba7dfaca98f4415667/num-200"],"report_directory":"/var/tmp/runner/_work/5584f24c54eff-24-02-21/lurk-rs/lurk-rs/target/criterion/reports/LEM Fibonacci Prove - rc = 100"}
{"reason":"benchmark-complete","id":"LEM Fibonacci Prove - rc = 600/ref=359e6a17ae371af4585cceba7dfaca98f4415667/num-100","report_directory":"/var/tmp/runner/_work/5584f24c54eff-24-02-21/lurk-rs/lurk-rs/target/criterion/reports/LEM Fibonacci Prove - rc = 600/ref=359e6a17ae371af4585cceba7dfaca98f4415667/num-100","iteration_count":[1,1,1,1,1,1,1,1,1,1],"measured_values":[1881818007.0,1826464637.0,1827876849.0,1832413879.0,1833007050.0,1827956107.0,1834559859.0,1834685038.0,1835821556.0,1833686560.0],"unit":"ns","throughput":[{"per_iteration":1200,"unit":"elements"}],"typical":{"estimate":1836828954.2,"lower_bound":1830255415.8,"upper_bound":1847548857.72,"unit":"ns"},"mean":{"estimate":1836828954.2,"lower_bound":1830255415.8,"upper_bound":1847548857.72,"unit":"ns"},"median":{"estimate":1833346805.0,"lower_bound":1827956107.0,"upper_bound":1835190707.5,"unit":"ns"},"median_abs_dev":{"estimate":2826564.9890184402,"lower_bound":740171.728259325,"upper_bound":9156629.358637333,"unit":"ns"},"slope":null,"change":null}
{"reason":"benchmark-complete","id":"LEM Fibonacci Prove - rc = 600/ref=359e6a17ae371af4585cceba7dfaca98f4415667/num-200","report_directory":"/var/tmp/runner/_work/5584f24c54eff-24-02-21/lurk-rs/lurk-rs/target/criterion/reports/LEM Fibonacci Prove - rc = 600/ref=359e6a17ae371af4585cceba7dfaca98f4415667/num-200","iteration_count":[1,1,1,1,1,1,1,1,1,1],"measured_values":[3030802229.0,3034376761.0,3036403957.0,3033136921.0,3025249334.0,3058339367.0,3055514983.0,3036742402.0,3031884457.0,3032055579.0],"unit":"ns","throughput":[{"per_iteration":1800,"unit":"elements"}],"typical":{"estimate":3037450599.0,"lower_bound":3031812387.6,"upper_bound":3044365817.0175,"unit":"ns"},"mean":{"estimate":3037450599.0,"lower_bound":3031812387.6,"upper_bound":3044365817.0175,"unit":"ns"},"median":{"estimate":3033756841.0,"lower_bound":3031428904.0,"upper_bound":3045959470.0,"unit":"ns"},"median_abs_dev":{"estimate":4152560.892677307,"lower_bound":928451.5467166901,"upper_bound":16009829.870268703,"unit":"ns"},"slope":null,"change":null}
{"reason":"group-complete","group_name":"LEM Fibonacci Prove - rc = 600","benchmarks":["LEM Fibonacci Prove - rc = 600/ref=359e6a17ae371af4585cceba7dfaca98f4415667/num-100","LEM Fibonacci Prove - rc = 600/ref=359e6a17ae371af4585cceba7dfaca98f4415667/num-200"],"report_directory":"/var/tmp/runner/_work/5584f24c54eff-24-02-21/lurk-rs/lurk-rs/target/criterion/reports/LEM Fibonacci Prove - rc = 600"}
